<?xml version="1.0" encoding="utf-8"?>
<SoundBanksInfo Platform="Windows" BasePlatform="Windows" SchemaVersion="16" SoundBankVersion="150">
	<RootPaths>
		<ProjectRoot>../..</ProjectRoot>
		<SourceFilesRoot>../../.cache/Windows</SourceFilesRoot>
		<SoundBanksRoot>.</SoundBanksRoot>
		<ExternalSourcesInputFile></ExternalSourcesInputFile>
		<ExternalSourcesOutputRoot>.</ExternalSourcesOutputRoot>
	</RootPaths>
	<DialogueEvents/>
	<SoundBanks>
		<SoundBank Id="1355168291" Type="User" GUID="{701ECBBD-9C7B-4030-8CDB-749EE5D1C7B9}" Language="SFX" Hash="{CC2176A8-8FB3-D046-F303-77E5148F3BB0}">
			<ObjectPath>Init</ObjectPath>
			<ShortName>Init</ShortName>
			<Path>Init.bnk</Path>
			<Plugins>
				<AudioDevices>
					<Plugin Id="2317455096" Name="No_Output" ObjectPath="\Audio Devices\Default Work Unit\No_Output" GUID="{5C9D1D71-F93C-479C-B1B2-0CFB3B0FDFD4}" LibName="No Output" LibId="11862023"/>
					<Plugin Id="3859886410" Name="System" ObjectPath="\Audio Devices\Default Work Unit\System" GUID="{EB945E00-7595-443B-95C2-270F7A24EF10}" LibName="System" LibId="11403271"/>
				</AudioDevices>
			</Plugins>
			<Busses>
				<Bus Id="3803692087" Name="Master Audio Bus" ObjectPath="\Master-Mixer Hierarchy\Default Work Unit\Master Audio Bus" GUID="{1514A4D8-1DA6-412A-A17E-75CA0C2149F3}"/>
			</Busses>
			<GameParameters>
				<GameParameter Id="822163944" Name="SS_Air_RPM" ObjectPath="\Game Parameters\Factory Soundseed Air Game Syncs\SS_Air_RPM" GUID="{A34890AB-B9D5-4526-A64D-5290C43EF2DC}"/>
				<GameParameter Id="1029930033" Name="SS_Air_Fury" ObjectPath="\Game Parameters\Factory Soundseed Air Game Syncs\SS_Air_Fury" GUID="{A2AE79DC-CA3A-46BA-9652-9986C322A87B}"/>
				<GameParameter Id="1351367891" Name="SS_Air_Fear" ObjectPath="\Game Parameters\Factory Soundseed Air Game Syncs\SS_Air_Fear" GUID="{F72E0659-4346-4E1C-A1B1-DAB46A05101E}"/>
				<GameParameter Id="2648548617" Name="SS_Air_Month" ObjectPath="\Game Parameters\Factory Soundseed Air Game Syncs\SS_Air_Month" GUID="{09E2B445-C4A3-447F-B3CA-818A1D925EF7}"/>
				<GameParameter Id="3002758120" Name="SS_Air_Freefall" ObjectPath="\Game Parameters\Factory Soundseed Air Game Syncs\SS_Air_Freefall" GUID="{2F2DFE37-4F9E-4D94-83D8-53CCA39781AD}"/>
				<GameParameter Id="3074696722" Name="SS_Air_Size" ObjectPath="\Game Parameters\Factory Soundseed Air Game Syncs\SS_Air_Size" GUID="{1329EBEF-A193-472E-A38C-64668B494879}"/>
				<GameParameter Id="3182548923" Name="Footstep_Speed" ObjectPath="\Game Parameters\Default Work Unit\Footstep_Speed" GUID="{EEA2077F-37D4-4AA1-9BEC-7F68FCC75BBC}"/>
				<GameParameter Id="3203397129" Name="SS_Air_TimeOfDay" ObjectPath="\Game Parameters\Factory Soundseed Air Game Syncs\SS_Air_TimeOfDay" GUID="{536FA72C-8C7E-4C8B-AE03-EF34FDADC314}"/>
				<GameParameter Id="3715662592" Name="SS_Air_Storm" ObjectPath="\Game Parameters\Factory Soundseed Air Game Syncs\SS_Air_Storm" GUID="{E93F8CDB-06D1-4737-ACAF-7CD44BBED783}"/>
				<GameParameter Id="3847924954" Name="SS_Air_Presence" ObjectPath="\Game Parameters\Factory Soundseed Air Game Syncs\SS_Air_Presence" GUID="{E3B7811A-7B2F-490F-B44F-5FE51B468041}"/>
				<GameParameter Id="4160247818" Name="SS_Air_Turbulence" ObjectPath="\Game Parameters\Factory Soundseed Air Game Syncs\SS_Air_Turbulence" GUID="{EDA87B19-73AA-40A0-9F19-2073606DB710}"/>
			</GameParameters>
			<SwitchGroups>
				<SwitchGroup Id="3932021394" Name="Footsteps_Texture" ObjectPath="\Switches\Default Work Unit\Footsteps_Texture" GUID="{48B9DB9A-DDA1-4B11-B59B-CA864B0B8469}">
					<Switches>
						<Switch Id="1850388778" Name="Desert" ObjectPath="\Switches\Default Work Unit\Footsteps_Texture\Desert" GUID="{5FD8BF1A-94E5-41AD-AA5E-F2960ACD89DB}"/>
						<Switch Id="1936566391" Name="DarkWorld" ObjectPath="\Switches\Default Work Unit\Footsteps_Texture\DarkWorld" GUID="{DD67C586-FED1-4D48-AE6C-B0A2A5F59F4D}"/>
					</Switches>
				</SwitchGroup>
			</SwitchGroups>
			<AcousticTextures>
				<AcousticTexture Id="504532776" Name="Brick" ObjectPath="\Virtual Acoustics\Factory Acoustic Textures\Textures\Brick" GUID="{B086A5A9-F204-4C53-A838-BDB18B18F6D6}">
					<Properties>
						<Property Name="AbsorptionLow" Type="Real32" Value="12"/>
						<Property Name="AbsorptionMidLow" Type="Real32" Value="18"/>
						<Property Name="AbsorptionMidHigh" Type="Real32" Value="23"/>
						<Property Name="AbsorptionHigh" Type="Real32" Value="35"/>
						<Property Name="Scattering" Type="Real32" Value="0"/>
					</Properties>
				</AcousticTexture>
				<AcousticTexture Id="513139656" Name="Mountain" ObjectPath="\Virtual Acoustics\Factory Acoustic Textures\Textures\Mountain" GUID="{C5933731-001A-4AB4-98DD-9B033A8C8EAB}">
					<Properties>
						<Property Name="AbsorptionLow" Type="Real32" Value="0"/>
						<Property Name="AbsorptionMidLow" Type="Real32" Value="0"/>
						<Property Name="AbsorptionMidHigh" Type="Real32" Value="0"/>
						<Property Name="AbsorptionHigh" Type="Real32" Value="0"/>
						<Property Name="Scattering" Type="Real32" Value="0"/>
					</Properties>
				</AcousticTexture>
				<AcousticTexture Id="841620460" Name="Concrete" ObjectPath="\Virtual Acoustics\Factory Acoustic Textures\Textures\Concrete" GUID="{5CF81C00-2896-4AE0-AF7C-3080BDABA682}">
					<Properties>
						<Property Name="AbsorptionLow" Type="Real32" Value="6"/>
						<Property Name="AbsorptionMidLow" Type="Real32" Value="6"/>
						<Property Name="AbsorptionMidHigh" Type="Real32" Value="6"/>
						<Property Name="AbsorptionHigh" Type="Real32" Value="14"/>
						<Property Name="Scattering" Type="Real32" Value="0"/>
					</Properties>
				</AcousticTexture>
				<AcousticTexture Id="1755085759" Name="Wood_Deep" ObjectPath="\Virtual Acoustics\Factory Acoustic Textures\Textures\Wood_Deep" GUID="{5246478E-C5DA-4E0C-A0DE-C98D1479529A}">
					<Properties>
						<Property Name="AbsorptionLow" Type="Real32" Value="1"/>
						<Property Name="AbsorptionMidLow" Type="Real32" Value="8"/>
						<Property Name="AbsorptionMidHigh" Type="Real32" Value="20"/>
						<Property Name="AbsorptionHigh" Type="Real32" Value="35"/>
						<Property Name="Scattering" Type="Real32" Value="0"/>
					</Properties>
				</AcousticTexture>
				<AcousticTexture Id="1873957695" Name="Anechoic" ObjectPath="\Virtual Acoustics\Factory Acoustic Textures\Textures\Anechoic" GUID="{8B0AC232-02E2-4EDE-BEAC-FDD1A900E3ED}">
					<Properties>
						<Property Name="AbsorptionLow" Type="Real32" Value="100"/>
						<Property Name="AbsorptionMidLow" Type="Real32" Value="100"/>
						<Property Name="AbsorptionMidHigh" Type="Real32" Value="100"/>
						<Property Name="AbsorptionHigh" Type="Real32" Value="100"/>
						<Property Name="Scattering" Type="Real32" Value="0"/>
					</Properties>
				</AcousticTexture>
				<AcousticTexture Id="1970351858" Name="Fabric" ObjectPath="\Virtual Acoustics\Factory Acoustic Textures\Textures\Fabric" GUID="{8381D532-DB6E-4EED-A7A3-BC7B0A0B8BA8}">
					<Properties>
						<Property Name="AbsorptionLow" Type="Real32" Value="3"/>
						<Property Name="AbsorptionMidLow" Type="Real32" Value="13"/>
						<Property Name="AbsorptionMidHigh" Type="Real32" Value="48"/>
						<Property Name="AbsorptionHigh" Type="Real32" Value="72"/>
						<Property Name="Scattering" Type="Real32" Value="0"/>
					</Properties>
				</AcousticTexture>
				<AcousticTexture Id="2058049674" Name="Wood" ObjectPath="\Virtual Acoustics\Factory Acoustic Textures\Textures\Wood" GUID="{1FFFBC96-6FE7-489E-BA6C-7C14A71391AE}">
					<Properties>
						<Property Name="AbsorptionLow" Type="Real32" Value="32"/>
						<Property Name="AbsorptionMidLow" Type="Real32" Value="25"/>
						<Property Name="AbsorptionMidHigh" Type="Real32" Value="20"/>
						<Property Name="AbsorptionHigh" Type="Real32" Value="35"/>
						<Property Name="Scattering" Type="Real32" Value="0"/>
					</Properties>
				</AcousticTexture>
				<AcousticTexture Id="2412606308" Name="Carpet" ObjectPath="\Virtual Acoustics\Factory Acoustic Textures\Textures\Carpet" GUID="{34227589-DC56-4260-96C4-B9F4B669092B}">
					<Properties>
						<Property Name="AbsorptionLow" Type="Real32" Value="46"/>
						<Property Name="AbsorptionMidLow" Type="Real32" Value="45"/>
						<Property Name="AbsorptionMidHigh" Type="Real32" Value="76"/>
						<Property Name="AbsorptionHigh" Type="Real32" Value="100"/>
						<Property Name="Scattering" Type="Real32" Value="0"/>
					</Properties>
				</AcousticTexture>
				<AcousticTexture Id="2637588553" Name="Tile" ObjectPath="\Virtual Acoustics\Factory Acoustic Textures\Textures\Tile" GUID="{A882DAC4-132A-47B7-BA9D-B9907BA29CC0}">
					<Properties>
						<Property Name="AbsorptionLow" Type="Real32" Value="67"/>
						<Property Name="AbsorptionMidLow" Type="Real32" Value="41"/>
						<Property Name="AbsorptionMidHigh" Type="Real32" Value="12"/>
						<Property Name="AbsorptionHigh" Type="Real32" Value="0"/>
						<Property Name="Scattering" Type="Real32" Value="0"/>
					</Properties>
				</AcousticTexture>
				<AcousticTexture Id="2928161104" Name="Curtains" ObjectPath="\Virtual Acoustics\Factory Acoustic Textures\Textures\Curtains" GUID="{F8E69E33-5C97-4968-B508-A1535F2D66E8}">
					<Properties>
						<Property Name="AbsorptionLow" Type="Real32" Value="7"/>
						<Property Name="AbsorptionMidLow" Type="Real32" Value="60"/>
						<Property Name="AbsorptionMidHigh" Type="Real32" Value="0"/>
						<Property Name="AbsorptionHigh" Type="Real32" Value="84"/>
						<Property Name="Scattering" Type="Real32" Value="0"/>
					</Properties>
				</AcousticTexture>
				<AcousticTexture Id="3195498748" Name="Cork_Tiles" ObjectPath="\Virtual Acoustics\Factory Acoustic Textures\Textures\Cork_Tiles" GUID="{30D2C919-925F-4143-8906-3DBB3C4AE5E2}">
					<Properties>
						<Property Name="AbsorptionLow" Type="Real32" Value="14"/>
						<Property Name="AbsorptionMidLow" Type="Real32" Value="30"/>
						<Property Name="AbsorptionMidHigh" Type="Real32" Value="73"/>
						<Property Name="AbsorptionHigh" Type="Real32" Value="100"/>
						<Property Name="Scattering" Type="Real32" Value="0"/>
					</Properties>
				</AcousticTexture>
				<AcousticTexture Id="3670307564" Name="Drywall" ObjectPath="\Virtual Acoustics\Factory Acoustic Textures\Textures\Drywall" GUID="{68A4E3F4-4C0B-4687-A8B8-A84DB93DBC8F}">
					<Properties>
						<Property Name="AbsorptionLow" Type="Real32" Value="2"/>
						<Property Name="AbsorptionMidLow" Type="Real32" Value="2"/>
						<Property Name="AbsorptionMidHigh" Type="Real32" Value="2"/>
						<Property Name="AbsorptionHigh" Type="Real32" Value="2"/>
						<Property Name="Scattering" Type="Real32" Value="0"/>
					</Properties>
				</AcousticTexture>
				<AcousticTexture Id="4168643977" Name="Acoustic_Banner" ObjectPath="\Virtual Acoustics\Factory Acoustic Textures\Textures\Acoustic_Banner" GUID="{2F2D53F2-DACC-408E-8B88-98B1B52A26D6}">
					<Properties>
						<Property Name="AbsorptionLow" Type="Real32" Value="37"/>
						<Property Name="AbsorptionMidLow" Type="Real32" Value="100"/>
						<Property Name="AbsorptionMidHigh" Type="Real32" Value="100"/>
						<Property Name="AbsorptionHigh" Type="Real32" Value="100"/>
						<Property Name="Scattering" Type="Real32" Value="0"/>
					</Properties>
				</AcousticTexture>
				<AcousticTexture Id="4262522749" Name="Wood_Bright" ObjectPath="\Virtual Acoustics\Factory Acoustic Textures\Textures\Wood_Bright" GUID="{7B85D1E5-C1A2-4E63-9A13-CEC54B641ADC}">
					<Properties>
						<Property Name="AbsorptionLow" Type="Real32" Value="32"/>
						<Property Name="AbsorptionMidLow" Type="Real32" Value="25"/>
						<Property Name="AbsorptionMidHigh" Type="Real32" Value="10"/>
						<Property Name="AbsorptionHigh" Type="Real32" Value="9"/>
						<Property Name="Scattering" Type="Real32" Value="0"/>
					</Properties>
				</AcousticTexture>
			</AcousticTextures>
		</SoundBank>
		<SoundBank Id="1584861542" Type="User" GUID="{06E0C42E-B84B-463D-80C1-55C828A882EB}" Language="SFX" Hash="{7B095F21-B533-9742-B84F-CC24E03E8AF9}">
			<ObjectPath>\SoundBanks\Default Work Unit\SB</ObjectPath>
			<ShortName>SB</ShortName>
			<Path>SB.bnk</Path>
			<Media>
				<File Id="40562976" Language="SFX" Streaming="false" Location="Memory">
					<ShortName>3D_Map02_Ambience_Loop_04.wav</ShortName>
					<CachePath>SFX/3D_Map02_Ambience_Loop_04_818F3B66.wem</CachePath>
				</File>
				<File Id="64788660" Language="SFX" Streaming="false" Location="Memory">
					<ShortName>2D_Map01_Ambience_Loop_02_03.wav</ShortName>
					<CachePath>SFX/2D_Map01_Ambience_Loop_02_03_818F3B66.wem</CachePath>
				</File>
				<File Id="70996195" Language="SFX" Streaming="false" Location="Memory">
					<ShortName>Fire_Loop_01.wav</ShortName>
					<CachePath>SFX/Fire_Loop_01_818F3B66.wem</CachePath>
				</File>
				<File Id="80235698" Language="SFX" Streaming="false" Location="Memory">
					<ShortName>Footstep_Texture01_05.wav</ShortName>
					<CachePath>SFX/Footstep_Texture01_05_818F3B66.wem</CachePath>
				</File>
				<File Id="102252990" Language="SFX" Streaming="false" Location="Memory">
					<ShortName>Skill_Projectile_02.wav</ShortName>
					<CachePath>SFX/Skill_Projectile_02_818F3B66.wem</CachePath>
				</File>
				<File Id="110245815" Language="SFX" Streaming="false" Location="Memory">
					<ShortName>2D_Map02_Ambience_Loop_02_01.wav</ShortName>
					<CachePath>SFX/2D_Map02_Ambience_Loop_02_01_818F3B66.wem</CachePath>
				</File>
				<File Id="120128966" Language="SFX" Streaming="false" Location="Memory">
					<ShortName>Skill_Projectile_03.wav</ShortName>
					<CachePath>SFX/Skill_Projectile_03_818F3B66.wem</CachePath>
				</File>
				<File Id="128094582" Language="SFX" Streaming="false" Location="Memory">
					<ShortName>2D_Map02_Ambience_Loop_02_03.wav</ShortName>
					<CachePath>SFX/2D_Map02_Ambience_Loop_02_03_818F3B66.wem</CachePath>
				</File>
				<File Id="132085907" Language="SFX" Streaming="false" Location="Memory">
					<ShortName>Footstep_Boots01_04.wav</ShortName>
					<CachePath>SFX/Footstep_Boots01_04_818F3B66.wem</CachePath>
				</File>
				<File Id="144690714" Language="SFX" Streaming="false" Location="Memory">
					<ShortName>Footstep_Boots01_05.wav</ShortName>
					<CachePath>SFX/Footstep_Boots01_05_818F3B66.wem</CachePath>
				</File>
				<File Id="146584187" Language="SFX" Streaming="false" Location="Memory">
					<ShortName>Skill_Hit_ 02.wav</ShortName>
					<CachePath>SFX/Skill_Hit_ 02_818F3B66.wem</CachePath>
				</File>
				<File Id="164114561" Language="SFX" Streaming="false" Location="Memory">
					<ShortName>2D_Map01_Ambience_Loop_01_03.wav</ShortName>
					<CachePath>SFX/2D_Map01_Ambience_Loop_01_03_818F3B66.wem</CachePath>
				</File>
				<File Id="179606090" Language="SFX" Streaming="false" Location="Memory">
					<ShortName>3D_Map02_Ambience_Loop_03.wav</ShortName>
					<CachePath>SFX/3D_Map02_Ambience_Loop_03_818F3B66.wem</CachePath>
				</File>
				<File Id="196069735" Language="SFX" Streaming="false" Location="Memory">
					<ShortName>Footstep_Boots01_03.wav</ShortName>
					<CachePath>SFX/Footstep_Boots01_03_818F3B66.wem</CachePath>
				</File>
				<File Id="199155045" Language="SFX" Streaming="false" Location="Memory">
					<ShortName>Armor Foley_05.wav</ShortName>
					<CachePath>SFX/Armor Foley_05_1B5F2174.wem</CachePath>
				</File>
				<File Id="219880325" Language="SFX" Streaming="false" Location="Memory">
					<ShortName>Skill_Projectile_01.wav</ShortName>
					<CachePath>SFX/Skill_Projectile_01_818F3B66.wem</CachePath>
				</File>
				<File Id="226569377" Language="SFX" Streaming="false" Location="Memory">
					<ShortName>Footstep_Boots01_07.wav</ShortName>
					<CachePath>SFX/Footstep_Boots01_07_818F3B66.wem</CachePath>
				</File>
				<File Id="241388928" Language="SFX" Streaming="false" Location="Memory">
					<ShortName>Armor Foley_01.wav</ShortName>
					<CachePath>SFX/Armor Foley_01_C991E1F5.wem</CachePath>
				</File>
				<File Id="243192686" Language="SFX" Streaming="false" Location="Memory">
					<ShortName>Footstep_Texture01_07.wav</ShortName>
					<CachePath>SFX/Footstep_Texture01_07_818F3B66.wem</CachePath>
				</File>
				<File Id="270630637" Language="SFX" Streaming="false" Location="Memory">
					<ShortName>Footstep_Texture01_01.wav</ShortName>
					<CachePath>SFX/Footstep_Texture01_01_818F3B66.wem</CachePath>
				</File>
				<File Id="277493211" Language="SFX" Streaming="false" Location="Memory">
					<ShortName>2D_Map02_Ambience_Loop_02_02.wav</ShortName>
					<CachePath>SFX/2D_Map02_Ambience_Loop_02_02_818F3B66.wem</CachePath>
				</File>
				<File Id="293861200" Language="SFX" Streaming="false" Location="Memory">
					<ShortName>Footstep_Texture02_05.wav</ShortName>
					<CachePath>SFX/Footstep_Texture02_05_818F3B66.wem</CachePath>
				</File>
				<File Id="324364435" Language="SFX" Streaming="false" Location="Memory">
					<ShortName>Footstep_Texture02_06.wav</ShortName>
					<CachePath>SFX/Footstep_Texture02_06_818F3B66.wem</CachePath>
				</File>
				<File Id="356602993" Language="SFX" Streaming="false" Location="Memory">
					<ShortName>2D_Map01_Ambience_Loop_02_02.wav</ShortName>
					<CachePath>SFX/2D_Map01_Ambience_Loop_02_02_818F3B66.wem</CachePath>
				</File>
				<File Id="357190279" Language="SFX" Streaming="false" Location="Memory">
					<ShortName>S_AnimationPortal_01.wav</ShortName>
					<CachePath>SFX/S_AnimationPortal_01_818F3B66.wem</CachePath>
				</File>
				<File Id="365273511" Language="SFX" Streaming="false" Location="Memory">
					<ShortName>Armor Foley_04.wav</ShortName>
					<CachePath>SFX/Armor Foley_04_F637485C.wem</CachePath>
				</File>
				<File Id="369564659" Language="SFX" Streaming="false" Location="Memory">
					<ShortName>3D_Map02_Ambience_Loop_02.wav</ShortName>
					<CachePath>SFX/3D_Map02_Ambience_Loop_02_818F3B66.wem</CachePath>
				</File>
				<File Id="373262603" Language="SFX" Streaming="false" Location="Memory">
					<ShortName>Footstep_Texture02_01.wav</ShortName>
					<CachePath>SFX/Footstep_Texture02_01_818F3B66.wem</CachePath>
				</File>
				<File Id="377018277" Language="SFX" Streaming="false" Location="Memory">
					<ShortName>2D_Map02_Ambience_Loop_03_01.wav</ShortName>
					<CachePath>SFX/2D_Map02_Ambience_Loop_03_01_818F3B66.wem</CachePath>
				</File>
				<File Id="380918109" Language="SFX" Streaming="false" Location="Memory">
					<ShortName>Skill_Hit_ 03.wav</ShortName>
					<CachePath>SFX/Skill_Hit_ 03_818F3B66.wem</CachePath>
				</File>
				<File Id="388327730" Language="SFX" Streaming="false" Location="Memory">
					<ShortName>3D_Map02_Ambience_Loop_08.wav</ShortName>
					<CachePath>SFX/3D_Map02_Ambience_Loop_08_818F3B66.wem</CachePath>
				</File>
				<File Id="390593327" Language="SFX" Streaming="false" Location="Memory">
					<ShortName>3D_Map02_Ambience_Loop_09.wav</ShortName>
					<CachePath>SFX/3D_Map02_Ambience_Loop_09_818F3B66.wem</CachePath>
				</File>
				<File Id="410568002" Language="SFX" Streaming="false" Location="Memory">
					<ShortName>Footstep_Texture01_02.wav</ShortName>
					<CachePath>SFX/Footstep_Texture01_02_818F3B66.wem</CachePath>
				</File>
				<File Id="447012044" Language="SFX" Streaming="false" Location="Memory">
					<ShortName>2D_Map02_Ambience_Loop_01_03.wav</ShortName>
					<CachePath>SFX/2D_Map02_Ambience_Loop_01_03_818F3B66.wem</CachePath>
				</File>
				<File Id="454550250" Language="SFX" Streaming="false" Location="Memory">
					<ShortName>Armor Foley_02.wav</ShortName>
					<CachePath>SFX/Armor Foley_02_40FD3CF5.wem</CachePath>
				</File>
				<File Id="470734958" Language="SFX" Streaming="false" Location="Memory">
					<ShortName>Footstep_Boots01_06.wav</ShortName>
					<CachePath>SFX/Footstep_Boots01_06_818F3B66.wem</CachePath>
				</File>
				<File Id="502251961" Language="SFX" Streaming="false" Location="Memory">
					<ShortName>2D_Map02_Ambience_Loop_03_02.wav</ShortName>
					<CachePath>SFX/2D_Map02_Ambience_Loop_03_02_818F3B66.wem</CachePath>
				</File>
				<File Id="506833056" Language="SFX" Streaming="false" Location="Memory">
					<ShortName>Skill_Cast_01.wav</ShortName>
					<CachePath>SFX/Skill_Cast_01_818F3B66.wem</CachePath>
				</File>
				<File Id="527374628" Language="SFX" Streaming="false" Location="Memory">
					<ShortName>Skill_Shot_01.wav</ShortName>
					<CachePath>SFX/Skill_Shot_01_818F3B66.wem</CachePath>
				</File>
				<File Id="538028814" Language="SFX" Streaming="false" Location="Memory">
					<ShortName>Skill_Shot_02.wav</ShortName>
					<CachePath>SFX/Skill_Shot_02_818F3B66.wem</CachePath>
				</File>
				<File Id="563275689" Language="SFX" Streaming="false" Location="Memory">
					<ShortName>Footstep_Texture02_02.wav</ShortName>
					<CachePath>SFX/Footstep_Texture02_02_818F3B66.wem</CachePath>
				</File>
				<File Id="566118984" Language="SFX" Streaming="false" Location="Memory">
					<ShortName>S_AnimationFadeOut_02.wav</ShortName>
					<CachePath>SFX/S_AnimationFadeOut_02_983EE4E9.wem</CachePath>
				</File>
				<File Id="582557018" Language="SFX" Streaming="false" Location="Memory">
					<ShortName>Skill_Shot_03.wav</ShortName>
					<CachePath>SFX/Skill_Shot_03_818F3B66.wem</CachePath>
				</File>
				<File Id="645986931" Language="SFX" Streaming="false" Location="Memory">
					<ShortName>3D_Map01_Ambience_01_02.wav</ShortName>
					<CachePath>SFX/3D_Map01_Ambience_01_02_818F3B66.wem</CachePath>
				</File>
				<File Id="650816160" Language="SFX" Streaming="false" Location="Memory">
					<ShortName>Footstep_Texture01_06.wav</ShortName>
					<CachePath>SFX/Footstep_Texture01_06_818F3B66.wem</CachePath>
				</File>
				<File Id="659608350" Language="SFX" Streaming="false" Location="Memory">
					<ShortName>Footstep_Texture01_04.wav</ShortName>
					<CachePath>SFX/Footstep_Texture01_04_818F3B66.wem</CachePath>
				</File>
				<File Id="664944771" Language="SFX" Streaming="false" Location="Memory">
					<ShortName>Armor Foley_03.wav</ShortName>
					<CachePath>SFX/Armor Foley_03_580F738D.wem</CachePath>
				</File>
				<File Id="680013032" Language="SFX" Streaming="false" Location="Memory">
					<ShortName>2D_Map02_Ambience_Loop_01_02.wav</ShortName>
					<CachePath>SFX/2D_Map02_Ambience_Loop_01_02_818F3B66.wem</CachePath>
				</File>
				<File Id="699593375" Language="SFX" Streaming="false" Location="Memory">
					<ShortName>3D_Map02_Ambience_Loop_07.wav</ShortName>
					<CachePath>SFX/3D_Map02_Ambience_Loop_07_818F3B66.wem</CachePath>
				</File>
				<File Id="707385738" Language="SFX" Streaming="false" Location="Memory">
					<ShortName>2D_Map01_Ambience_Loop_01_02.wav</ShortName>
					<CachePath>SFX/2D_Map01_Ambience_Loop_01_02_818F3B66.wem</CachePath>
				</File>
				<File Id="722814120" Language="SFX" Streaming="false" Location="Memory">
					<ShortName>Teleport_Loop_01.wav</ShortName>
					<CachePath>SFX/Teleport_Loop_01_818F3B66.wem</CachePath>
				</File>
				<File Id="726288091" Language="SFX" Streaming="false" Location="Memory">
					<ShortName>3D_Map01_Ambience_01_01.wav</ShortName>
					<CachePath>SFX/3D_Map01_Ambience_01_01_818F3B66.wem</CachePath>
				</File>
				<File Id="734751421" Language="SFX" Streaming="false" Location="Memory">
					<ShortName>3D_Map02_Ambience_Loop_06.wav</ShortName>
					<CachePath>SFX/3D_Map02_Ambience_Loop_06_818F3B66.wem</CachePath>
				</File>
				<File Id="754076131" Language="SFX" Streaming="false" Location="Memory">
					<ShortName>2D_Map01_Ambience_Loop_02_01.wav</ShortName>
					<CachePath>SFX/2D_Map01_Ambience_Loop_02_01_818F3B66.wem</CachePath>
				</File>
				<File Id="780489615" Language="SFX" Streaming="false" Location="Memory">
					<ShortName>2D_Map01_Ambience_Loop_01_01.wav</ShortName>
					<CachePath>SFX/2D_Map01_Ambience_Loop_01_01_818F3B66.wem</CachePath>
				</File>
				<File Id="781750763" Language="SFX" Streaming="false" Location="Memory">
					<ShortName>Skill_Cast_02.wav</ShortName>
					<CachePath>SFX/Skill_Cast_02_818F3B66.wem</CachePath>
				</File>
				<File Id="795906522" Language="SFX" Streaming="false" Location="Memory">
					<ShortName>3D_Map02_Ambience_Loop_01.wav</ShortName>
					<CachePath>SFX/3D_Map02_Ambience_Loop_01_818F3B66.wem</CachePath>
				</File>
				<File Id="800853907" Language="SFX" Streaming="false" Location="Memory">
					<ShortName>2D_Map02_Ambience_Loop_03_03.wav</ShortName>
					<CachePath>SFX/2D_Map02_Ambience_Loop_03_03_818F3B66.wem</CachePath>
				</File>
				<File Id="802063852" Language="SFX" Streaming="false" Location="Memory">
					<ShortName>Footstep_Boots01_01.wav</ShortName>
					<CachePath>SFX/Footstep_Boots01_01_818F3B66.wem</CachePath>
				</File>
				<File Id="896642150" Language="SFX" Streaming="false" Location="Memory">
					<ShortName>2D_Map02_Ambience_Loop_01_01.wav</ShortName>
					<CachePath>SFX/2D_Map02_Ambience_Loop_01_01_818F3B66.wem</CachePath>
				</File>
				<File Id="928608727" Language="SFX" Streaming="false" Location="Memory">
					<ShortName>Footstep_Boots01_02.wav</ShortName>
					<CachePath>SFX/Footstep_Boots01_02_818F3B66.wem</CachePath>
				</File>
				<File Id="937452279" Language="SFX" Streaming="false" Location="Memory">
					<ShortName>Footstep_Texture01_03.wav</ShortName>
					<CachePath>SFX/Footstep_Texture01_03_818F3B66.wem</CachePath>
				</File>
				<File Id="954015879" Language="SFX" Streaming="false" Location="Memory">
					<ShortName>3D_Map01_Ambience_01_03.wav</ShortName>
					<CachePath>SFX/3D_Map01_Ambience_01_03_818F3B66.wem</CachePath>
				</File>
				<File Id="961782400" Language="SFX" Streaming="false" Location="Memory">
					<ShortName>Skill_Cast_Loop_03.wav</ShortName>
					<CachePath>SFX/Skill_Cast_Loop_03_D1861BF8.wem</CachePath>
				</File>
				<File Id="964698149" Language="SFX" Streaming="false" Location="Memory">
					<ShortName>Skill_Hit_ 01.wav</ShortName>
					<CachePath>SFX/Skill_Hit_ 01_818F3B66.wem</CachePath>
				</File>
				<File Id="996980279" Language="SFX" Streaming="false" Location="Memory">
					<ShortName>3D_Map02_Ambience_Loop_05.wav</ShortName>
					<CachePath>SFX/3D_Map02_Ambience_Loop_05_818F3B66.wem</CachePath>
				</File>
				<File Id="997261430" Language="SFX" Streaming="false" Location="Memory">
					<ShortName>Skill_Cast_Loop_02.wav</ShortName>
					<CachePath>SFX/Skill_Cast_Loop_02_160B8FA5.wem</CachePath>
				</File>
				<File Id="999858282" Language="SFX" Streaming="false" Location="Memory">
					<ShortName>Skill_Cast_Loop_01.wav</ShortName>
					<CachePath>SFX/Skill_Cast_Loop_01_3CA15333.wem</CachePath>
				</File>
				<File Id="1006875835" Language="SFX" Streaming="false" Location="Memory">
					<ShortName>Footstep_Texture02_03.wav</ShortName>
					<CachePath>SFX/Footstep_Texture02_03_818F3B66.wem</CachePath>
				</File>
				<File Id="1026784446" Language="SFX" Streaming="false" Location="Memory">
					<ShortName>Skill_Cast_03.wav</ShortName>
					<CachePath>SFX/Skill_Cast_03_818F3B66.wem</CachePath>
				</File>
				<File Id="1049279678" Language="SFX" Streaming="false" Location="Memory">
					<ShortName>Footstep_Texture02_07.wav</ShortName>
					<CachePath>SFX/Footstep_Texture02_07_818F3B66.wem</CachePath>
				</File>
				<File Id="1059799545" Language="SFX" Streaming="false" Location="Memory">
					<ShortName>Footstep_Texture02_04.wav</ShortName>
					<CachePath>SFX/Footstep_Texture02_04_818F3B66.wem</CachePath>
				</File>
			</Media>
			<Events>
				<Event Id="784914450" Name="Play_2D_Map01_Ambience_Loop" ObjectPath="\Events\Default Work Unit\Play_Events\Play_2D_Map01_Ambience_Loop" GUID="{345B9DB2-910E-4EE0-BC39-EBF7FB9AB5CD}" DurationType="Infinite">
					<MediaRefs>
						<MediaRef Id="64788660"/>
						<MediaRef Id="164114561"/>
						<MediaRef Id="356602993"/>
						<MediaRef Id="707385738"/>
						<MediaRef Id="754076131"/>
						<MediaRef Id="780489615"/>
					</MediaRefs>
				</Event>
				<Event Id="1612719477" Name="Play_2D_Map02_Ambience_Loop" ObjectPath="\Events\Default Work Unit\Play_Events\Play_2D_Map02_Ambience_Loop" GUID="{4771711F-BB47-4C07-AE2D-3046CB22BFED}" DurationType="Infinite">
					<MediaRefs>
						<MediaRef Id="110245815"/>
						<MediaRef Id="128094582"/>
						<MediaRef Id="277493211"/>
						<MediaRef Id="377018277"/>
						<MediaRef Id="447012044"/>
						<MediaRef Id="502251961"/>
						<MediaRef Id="680013032"/>
						<MediaRef Id="800853907"/>
						<MediaRef Id="896642150"/>
					</MediaRefs>
				</Event>
				<Event Id="3097540376" Name="Play_3D_Map01_Ambience" ObjectPath="\Events\Default Work Unit\Play_Events\Play_3D_Map01_Ambience" GUID="{342FD0EA-F303-46D3-970A-6D25F5919A61}" MaxAttenuation="100" DurationType="Infinite">
					<MediaRefs>
						<MediaRef Id="645986931"/>
						<MediaRef Id="726288091"/>
						<MediaRef Id="954015879"/>
					</MediaRefs>
				</Event>
				<Event Id="1130970705" Name="Play_3D_Map02_Ambience_Crow" ObjectPath="\Events\Default Work Unit\Play_Events\Play_3D_Map02_Ambience_Crow" GUID="{72DC42D1-DB7C-4E56-86BF-223E03C5DCFF}" MaxAttenuation="100" DurationType="Infinite">
					<MediaRefs>
						<MediaRef Id="40562976"/>
						<MediaRef Id="734751421"/>
						<MediaRef Id="996980279"/>
					</MediaRefs>
				</Event>
				<Event Id="3900994105" Name="Play_3D_Map02_Ambience_Ghost" ObjectPath="\Events\Default Work Unit\Play_Events\Play_3D_Map02_Ambience_Ghost" GUID="{7060C863-A7D9-4B6F-8A07-D2038DFA82BE}" MaxAttenuation="100" DurationType="Infinite">
					<MediaRefs>
						<MediaRef Id="388327730"/>
						<MediaRef Id="390593327"/>
						<MediaRef Id="699593375"/>
					</MediaRefs>
				</Event>
				<Event Id="3235615986" Name="Play_3D_Map02_Ambience_Thunder" ObjectPath="\Events\Default Work Unit\Play_Events\Play_3D_Map02_Ambience_Thunder" GUID="{4632FE19-3304-40AA-AA7D-5A3EDACDCD27}" MaxAttenuation="100" DurationType="Infinite">
					<MediaRefs>
						<MediaRef Id="179606090"/>
						<MediaRef Id="369564659"/>
						<MediaRef Id="795906522"/>
					</MediaRefs>
				</Event>
				<Event Id="1779335" Name="Play_Fire_Loop" ObjectPath="\Events\Default Work Unit\Play_Events\Play_Fire_Loop" GUID="{66C314EC-925C-428E-8B1E-9CA9745CF899}" MaxAttenuation="700" DurationType="Infinite">
					<MediaRefs>
						<MediaRef Id="70996195"/>
					</MediaRefs>
				</Event>
				<Event Id="3310393073" Name="Play_PC_Armor" ObjectPath="\Events\Default Work Unit\Play_Events\Play_PC_Armor" GUID="{55D7A62B-6634-42F8-A90A-4EF87BCD551E}" DurationType="OneShot" DurationMin="0.45850202" DurationMax="0.59977925">
					<MediaRefs>
						<MediaRef Id="199155045"/>
						<MediaRef Id="241388928"/>
						<MediaRef Id="365273511"/>
						<MediaRef Id="454550250"/>
						<MediaRef Id="664944771"/>
					</MediaRefs>
				</Event>
				<Event Id="634505947" Name="Play_PC_Footstpes" ObjectPath="\Events\Default Work Unit\Play_Events\Play_PC_Footstpes" GUID="{CD7D3C34-2003-4A9F-B9FF-53FBA1884D88}" DurationType="OneShot" DurationMin="0.3174957" DurationMax="0.35637692">
					<MediaRefs>
						<MediaRef Id="132085907"/>
						<MediaRef Id="144690714"/>
						<MediaRef Id="196069735"/>
						<MediaRef Id="226569377"/>
						<MediaRef Id="470734958"/>
						<MediaRef Id="802063852"/>
						<MediaRef Id="928608727"/>
					</MediaRefs>
					<SwitchContainers>
						<SwitchContainer>
							<SwitchValue GroupType="Switch" GroupId="3932021394" Id="1850388778" GUID="{5FD8BF1A-94E5-41AD-AA5E-F2960ACD89DB}" Default="true"/>
							<MediaRefs>
								<MediaRef Id="80235698"/>
								<MediaRef Id="243192686"/>
								<MediaRef Id="270630637"/>
								<MediaRef Id="410568002"/>
								<MediaRef Id="650816160"/>
								<MediaRef Id="659608350"/>
								<MediaRef Id="937452279"/>
							</MediaRefs>
						</SwitchContainer>
						<SwitchContainer>
							<SwitchValue GroupType="Switch" GroupId="3932021394" Id="1936566391" GUID="{DD67C586-FED1-4D48-AE6C-B0A2A5F59F4D}"/>
							<MediaRefs>
								<MediaRef Id="293861200"/>
								<MediaRef Id="324364435"/>
								<MediaRef Id="373262603"/>
								<MediaRef Id="563275689"/>
								<MediaRef Id="1006875835"/>
								<MediaRef Id="1049279678"/>
								<MediaRef Id="1059799545"/>
							</MediaRefs>
						</SwitchContainer>
						<SwitchContainer>
							<SwitchValue GroupType="Switch" GroupId="3932021394" Id="1850388778" GUID="{5FD8BF1A-94E5-41AD-AA5E-F2960ACD89DB}" Default="true"/>
							<MediaRefs>
								<MediaRef Id="80235698"/>
								<MediaRef Id="243192686"/>
								<MediaRef Id="270630637"/>
								<MediaRef Id="410568002"/>
								<MediaRef Id="650816160"/>
								<MediaRef Id="659608350"/>
								<MediaRef Id="937452279"/>
							</MediaRefs>
						</SwitchContainer>
						<SwitchContainer>
							<SwitchValue GroupType="Switch" GroupId="3932021394" Id="1936566391" GUID="{DD67C586-FED1-4D48-AE6C-B0A2A5F59F4D}"/>
							<MediaRefs>
								<MediaRef Id="293861200"/>
								<MediaRef Id="324364435"/>
								<MediaRef Id="373262603"/>
								<MediaRef Id="563275689"/>
								<MediaRef Id="1006875835"/>
								<MediaRef Id="1049279678"/>
								<MediaRef Id="1059799545"/>
							</MediaRefs>
						</SwitchContainer>
					</SwitchContainers>
				</Event>
				<Event Id="3045213307" Name="Play_PC_Skill_Cast" ObjectPath="\Events\Default Work Unit\Play_Events\Play_PC_Skill_Cast" GUID="{DE71FF76-D439-4218-883F-68980499D0CF}" DurationType="OneShot" DurationMin="6" DurationMax="6">
					<MediaRefs>
						<MediaRef Id="506833056"/>
						<MediaRef Id="781750763"/>
						<MediaRef Id="961782400"/>
						<MediaRef Id="997261430"/>
						<MediaRef Id="999858282"/>
						<MediaRef Id="1026784446"/>
					</MediaRefs>
				</Event>
				<Event Id="606933137" Name="Play_PC_Skill_Hit" ObjectPath="\Events\Default Work Unit\Play_Events\Play_PC_Skill_Hit" GUID="{016B3D46-908E-4F3E-93C1-DF71845D01AF}" DurationType="OneShot" DurationMin="5" DurationMax="5">
					<MediaRefs>
						<MediaRef Id="146584187"/>
						<MediaRef Id="380918109"/>
						<MediaRef Id="964698149"/>
					</MediaRefs>
				</Event>
				<Event Id="1944915683" Name="Play_PC_Skill_Projectile" ObjectPath="\Events\Default Work Unit\Play_Events\Play_PC_Skill_Projectile" GUID="{47CE7E1C-B672-494D-83B0-E82D5B02C8F8}" DurationType="OneShot" DurationMin="5.015" DurationMax="5.015">
					<MediaRefs>
						<MediaRef Id="102252990"/>
						<MediaRef Id="120128966"/>
						<MediaRef Id="219880325"/>
					</MediaRefs>
				</Event>
				<Event Id="3656471518" Name="Play_PC_Skill_Shot" ObjectPath="\Events\Default Work Unit\Play_Events\Play_PC_Skill_Shot" GUID="{5319D05E-BC1D-4CD6-AD29-19324F9CB37B}" DurationType="OneShot" DurationMin="5" DurationMax="5">
					<MediaRefs>
						<MediaRef Id="527374628"/>
						<MediaRef Id="538028814"/>
						<MediaRef Id="582557018"/>
					</MediaRefs>
				</Event>
				<Event Id="717465561" Name="Play_S_AnimationFadeOut_02" ObjectPath="\Events\Default Work Unit\Play_Events\Play_S_AnimationFadeOut_02" GUID="{0A6DCC7A-461A-49DB-BF2B-1BAD56BA7670}" DurationType="OneShot" DurationMin="9.5" DurationMax="9.5">
					<MediaRefs>
						<MediaRef Id="566118984"/>
					</MediaRefs>
				</Event>
				<Event Id="2011390394" Name="Play_S_AnimationPortal_01" ObjectPath="\Events\Default Work Unit\Play_Events\Play_S_AnimationPortal_01" GUID="{5A287577-D373-425C-89D1-DA6F0594A484}" DurationType="OneShot" DurationMin="10" DurationMax="10">
					<MediaRefs>
						<MediaRef Id="357190279"/>
					</MediaRefs>
				</Event>
				<Event Id="4098890576" Name="Play_Teleport_Loop" ObjectPath="\Events\Default Work Unit\Play_Events\Play_Teleport_Loop" GUID="{180A5464-CF1D-463C-8B00-0D7E15653275}" MaxAttenuation="1000" DurationType="Infinite">
					<MediaRefs>
						<MediaRef Id="722814120"/>
					</MediaRefs>
				</Event>
			</Events>
			<GameParameters>
				<GameParameter Id="3182548923" Name="Footstep_Speed" ObjectPath="\Game Parameters\Default Work Unit\Footstep_Speed" GUID="{EEA2077F-37D4-4AA1-9BEC-7F68FCC75BBC}"/>
			</GameParameters>
			<SwitchGroups>
				<SwitchGroup Id="3932021394" Name="Footsteps_Texture" ObjectPath="\Switches\Default Work Unit\Footsteps_Texture" GUID="{48B9DB9A-DDA1-4B11-B59B-CA864B0B8469}">
					<Switches>
						<Switch Id="1850388778" Name="Desert" ObjectPath="\Switches\Default Work Unit\Footsteps_Texture\Desert" GUID="{5FD8BF1A-94E5-41AD-AA5E-F2960ACD89DB}"/>
						<Switch Id="1936566391" Name="DarkWorld" ObjectPath="\Switches\Default Work Unit\Footsteps_Texture\DarkWorld" GUID="{DD67C586-FED1-4D48-AE6C-B0A2A5F59F4D}"/>
					</Switches>
				</SwitchGroup>
			</SwitchGroups>
		</SoundBank>
	</SoundBanks>
	<FileHash>{C7E90690-89A5-4363-5865-BEAA95DF56A0}</FileHash>
</SoundBanksInfo>
